uplink_httpx/__init__.py
uplink_httpx/client.py
uplink_httpx/consumer.py
uplink_httpx-2.1.dist-info/LICENSE
uplink_httpx-2.1.dist-info/METADATA
uplink_httpx-2.1.dist-info/WHEEL
uplink_httpx-2.1.dist-info/top_level.txt
uplink_httpx-2.1.dist-info/RECORD
