Metadata-Version: 2.1
Name: uplink-httpx
Version: 2.1
Summary: HttpX Client for Uplink
Home-page: https://github.com/chassing/uplink-httpx
Author: Christian Assing
Author-email: chris@ca-net.org
License: MIT License, Copyright (c) 2019 Christian Assing
Keywords: uplink,httpx,asyncio,rest
Platform: any
Classifier: Development Status :: 5 - Production/Stable
Classifier: Intended Audience :: Developers
Classifier: License :: OSI Approved :: MIT License
Classifier: Operating System :: OS Independent
Classifier: Programming Language :: Python :: 3.6
Classifier: Programming Language :: Python :: 3.7
Classifier: Programming Language :: Python :: 3.8
Classifier: Natural Language :: English
Classifier: Topic :: Internet :: WWW/HTTP
Classifier: Topic :: Software Development :: Libraries :: Python Modules
Requires-Dist: httpx
Requires-Dist: uplink
